{
  "hostgroup": {
    "id": "81",
    "name": "Clientes/Worldcargo"
  },
  "hosts": [
    {
      "id": "10659",
      "name": "Worldcargo - Sao Paulo",
      "graphs": [
        {
          "id": "4883",
          "name": "*CPU",
          "from_time": "2025-08-18 00:00:00",
          "to_time": "2025-08-24 23:59:59"
        },
        {
          "id": "4884",
          "name": "*Conexoes",
          "from_time": "2025-08-18 00:00:00",
          "to_time": "2025-08-24 23:59:59"
        },
        {
          "id": "4885",
          "name": "*RAM",
          "from_time": "2025-08-18 00:00:00",
          "to_time": "2025-08-24 23:59:59"
        },
        {
          "id": "4891",
          "name": "Disponibilidade - X1",
          "from_time": "2025-08-18 00:00:00",
          "to_time": "2025-08-24 23:59:59"
        },
        {
          "id": "4887",
          "name": "Trafego - X1 (WAN)",
          "from_time": "2025-08-18 00:00:00",
          "to_time": "2025-08-24 23:59:59"
        },
        {
          "id": "4892",
          "name": "Disponibilidade - X2",
          "from_time": "2025-08-18 00:00:00",
          "to_time": "2025-08-24 23:59:59"
        },
        {
          "id": "4888",
          "name": "Trafego - X2 (WAN)",
          "from_time": "2025-08-18 00:00:00",
          "to_time": "2025-08-24 23:59:59"
        },
        {
          "id": "4886",
          "name": "Trafego - X0 (Portshield Host)",
          "from_time": "2025-08-18 00:00:00",
          "to_time": "2025-08-24 23:59:59"
        },
        {
          "id": "4889",
          "name": "Trafego - X3 (Portshielded To X0)",
          "from_time": "2025-08-18 00:00:00",
          "to_time": "2025-08-24 23:59:59"
        },
        {
          "id": "4890",
          "name": "Trafego - X4 (Portshielded To X0)",
          "from_time": "2025-08-18 00:00:00",
          "to_time": "2025-08-24 23:59:59"
        }
      ]
    },
    {
      "id": "10658",
      "name": "Worldcargo - Santos",
      "graphs": [
        {
          "id": "4868",
          "name": "*CPU",
          "from_time": "2025-08-18 00:00:00",
          "to_time": "2025-08-24 23:59:59"
        },
        {
          "id": "4869",
          "name": "*Conexoes",
          "from_time": "2025-08-18 00:00:00",
          "to_time": "2025-08-24 23:59:59"
        },
        {
          "id": "4870",
          "name": "*RAM",
          "from_time": "2025-08-18 00:00:00",
          "to_time": "2025-08-24 23:59:59"
        },
        {
          "id": "4876",
          "name": "Disponibilidade - X1",
          "from_time": "2025-08-18 00:00:00",
          "to_time": "2025-08-24 23:59:59"
        },
        {
          "id": "4872",
          "name": "Trafego - X1 (WAN)",
          "from_time": "2025-08-18 00:00:00",
          "to_time": "2025-08-24 23:59:59"
        },
        {
          "id": "4877",
          "name": "Disponibilidade - X2",
          "from_time": "2025-08-18 00:00:00",
          "to_time": "2025-08-24 23:59:59"
        },
        {
          "id": "4873",
          "name": "Trafego - X2 (WAN)",
          "from_time": "2025-08-18 00:00:00",
          "to_time": "2025-08-24 23:59:59"
        },
        {
          "id": "4871",
          "name": "Trafego - X0 (Portshield Host)",
          "from_time": "2025-08-18 00:00:00",
          "to_time": "2025-08-24 23:59:59"
        },
        {
          "id": "4878",
          "name": "Latencia - X1",
          "from_time": "2025-08-18 00:00:00",
          "to_time": "2025-08-24 23:59:59"
        }
      ]
    }
  ],
  "summary": {
    "incidents": {
      "enabled": false,
      "value": 0
    },
    "openProblems": {
      "enabled": false,
      "value": [],
      "columns": [
        "name",
        "severity",
        "tags",
        "clock"
      ]
    },
    "topTriggers": {
      "enabled": false,
      "value": [],
      "chartType": "bar"
    }
  },
  "emails": [
    "thales.vieira@worldcargo.com.br",
    "tec@athenasecurity.com.br",
    "loltramari@athenasecurity.com.br"
  ],
  "frequency": "weekly",
  "logo_filename": "logohostgroup81.png",
  "analyst": "Leonardo Oltramari",
  "comments": "",
  "last_generated": "",
  "last_sent_period": "2025-33",
  "last_sent": "2025-08-28T12:22:56.878452"
}